README.md
pyproject.toml
setup.cfg
setup.py
schedule_service_client/__init__.py
schedule_service_client/api_client.py
schedule_service_client/api_response.py
schedule_service_client/configuration.py
schedule_service_client/exceptions.py
schedule_service_client/py.typed
schedule_service_client/rest.py
schedule_service_client.egg-info/PKG-INFO
schedule_service_client.egg-info/SOURCES.txt
schedule_service_client.egg-info/dependency_links.txt
schedule_service_client.egg-info/requires.txt
schedule_service_client.egg-info/top_level.txt
schedule_service_client/api/__init__.py
schedule_service_client/api/healthcheck_api.py
schedule_service_client/api/schedule_api.py
schedule_service_client/api/workbook_api.py
schedule_service_client/models/__init__.py
schedule_service_client/models/day.py
schedule_service_client/models/http_validation_error.py
schedule_service_client/models/lesson.py
schedule_service_client/models/platoon.py
schedule_service_client/models/schedule_result.py
schedule_service_client/models/shape.py
schedule_service_client/models/subject.py
schedule_service_client/models/validation_error.py
schedule_service_client/models/validation_error_loc_inner.py
schedule_service_client/models/week_date.py
schedule_service_client/models/week_schedule.py
schedule_service_client/models/week_schedule_result.py
schedule_service_client/models/workbook_file.py
schedule_service_client/models/workbook_settings.py
test/test_day.py
test/test_healthcheck_api.py
test/test_http_validation_error.py
test/test_lesson.py
test/test_platoon.py
test/test_schedule_api.py
test/test_schedule_result.py
test/test_shape.py
test/test_subject.py
test/test_validation_error.py
test/test_validation_error_loc_inner.py
test/test_week_date.py
test/test_week_schedule.py
test/test_week_schedule_result.py
test/test_workbook_api.py
test/test_workbook_file.py
test/test_workbook_settings.py