Metadata-Version: 2.1
Name: schedule-service-client
Version: 1.4.8
Summary: RTU MIREA VUC
Home-page: 
Author: OpenAPI Generator community
Author-email: team@openapitools.org
Keywords: OpenAPI,OpenAPI-Generator,RTU MIREA VUC
